README.md
setup.py
tap_linkedin_ads/__init__.py
tap_linkedin_ads/client.py
tap_linkedin_ads/discover.py
tap_linkedin_ads/schema.py
tap_linkedin_ads/streams.py
tap_linkedin_ads/sync.py
tap_linkedin_ads/transform.py
tap_linkedin_ads.egg-info/PKG-INFO
tap_linkedin_ads.egg-info/SOURCES.txt
tap_linkedin_ads.egg-info/dependency_links.txt
tap_linkedin_ads.egg-info/entry_points.txt
tap_linkedin_ads.egg-info/requires.txt
tap_linkedin_ads.egg-info/top_level.txt
tap_linkedin_ads/schemas/account_users.json
tap_linkedin_ads/schemas/accounts.json
tap_linkedin_ads/schemas/ad_analytics_by_campaign.json
tap_linkedin_ads/schemas/ad_analytics_by_creative.json
tap_linkedin_ads/schemas/campaign_groups.json
tap_linkedin_ads/schemas/campaigns.json
tap_linkedin_ads/schemas/creatives.json
tap_linkedin_ads/schemas/video_ads.json